{
  "request_id": "220707162914_6b539193-995f-517c-a20b-65a132cc4579",
  "status": "pending",
  "request": {
    "target_credentials": "d3c13e2a-e654-410d-9452-b34ed3f48b25",
    "source_settings": {
      "$schema": "https://s.y42.com/integrations/file-upload/0.0.0/source.json#csv"
    },
    "table_settings": {
      "$schema": "https://s.y42.com/integrations/file-upload/0.0.0/source.json#csv",
      "content-type": "text/csv",
      "uploadTarget": "https://storage.googleapis.com/upload/storage/v1/b/y42_betaonboarding_56f73616f4a340f3958391da0a802cc8/o?uploadType=resumable&upload_id=ADPycduNLdvWa6OuJ890wXDtel9EProu-v5WT0QBIWJnX5O4faJR2U5B-hM6MTIVqAGVwRjovYFqEKGCd4wP-43QxBdCTg",
      "originalName": "reviews.csv",
      "size": "2112243",
      "uri": "gs://y42_betaonboarding_56f73616f4a340f3958391da0a802cc8/userUploads/v2/41/file-upload/95c274e4-271f-4ab9-86c9-88436fd4e1f3",
      "csv_options": {
        "field_delimiter": ",",
        "allow_quoted_new_lines": true,
        "null_marker": "",
        "ignore_unknown_values": false,
        "encoding": "UTF-8",
        "quote": "\"",
        "skip_leading_rows": null
      }
    },
    "created_at": "2022-07-07T16:29:14.145085+00:00",
    "target": {
      "storage": {
        "type": "githubapp",
        "path": "/src/Integrations/facebook_data/reviews.csv",
        "id": "41:4e5151c8-9a50-4091-b95f-1feae9732614",
        "branch": "main"
      },
      "info": {
        "app_id": "",
        "owner": "brauliotegui",
        "repo": "y42_beta_onboarding_db",
        "commit_sha": "7f95138f35818728ea535b2fe13b891c0de34276"
      }
    },
    "context": {
      "company_id": 41,
      "company_slug": "tmnz",
      "triggered_by_type": "user",
      "triggered_by_id": "48",
      "trial": false
    }
  },
  "created_at": "2022-07-07T16:29:14.145085+00:00",
  "_signature": "87v1axWi9nA6ZVPQD0ciNicpmDRV2jVDUPxrQIbaMVr6dJQ0PzXP8FOI7robkYINnlGs5zkNH8UFc34eOSv2DA=="
}
